{
  "hydra:member": [
    {
      "id": "135651",
      "period": "daily",
      "reportType": "south",
      "dateImport": "2022-09-16T00:00:00.000000",
      "dateResult": "2022-09-15T00:00:00.000000",
      "ranking": "8",
      "description": "RTL INFO 13H",
      "category": null,
      "channel": "RTL-TVI",
      "dateDiff": "2022-09-15T00:00:00.000000",
      "startTime": "12:58:28",
      "rLength": "00:21:54",
      "ratePerc": null,
      "rateInK": "195.243",
      "shr": null,
      "description2": null,
      "rateInKAll": null,
      "live": 0
    },
    {
      "id": "135652",
      "period": "daily",
      "reportType": "south",
      "dateImport": "2022-09-16T00:00:00.000000",
      "dateResult": "2022-09-15T00:00:00.000000",
      "ranking": "9",
      "description": "PARENTS D'ELEVES",
      "category": null,
      "channel": "RTL-TVI",
      "dateDiff": "2022-09-15T00:00:00.000000",
      "startTime": "20:40:42",
      "rLength": "01:22:56",
      "ratePerc": null,
      "rateInK": "179.340",
      "shr": null,
      "description2": null,
      "rateInKAll": null,
      "live": 0
    },
    {
      "id": "135653",
      "period": "daily",
      "reportType": "south",
      "dateImport": "2022-09-16T00:00:00.000000",
      "dateResult": "2022-09-15T00:00:00.000000",
      "ranking": "10",
      "description": "ICI TOUT COMMENCE",
      "category": null,
      "channel": "La Une",
      "dateDiff": "2022-09-15T00:00:00.000000",
      "startTime": "17:19:29",
      "rLength": "00:29:19",
      "ratePerc": null,
      "rateInK": "170.340",
      "shr": null,
      "description2": null,
      "rateInKAll": null,
      "live": 0
    },
    {
      "id": "135654",
      "period": "daily",
      "reportType": "south",
      "dateImport": "2022-09-16T00:00:00.000000",
      "dateResult": "2022-09-15T00:00:00.000000",
      "ranking": "11",
      "description": "FOOT. C4 UEFA - FCSB/ANDERLECHT",
      "category": null,
      "channel": "Tipik",
      "dateDiff": "2022-09-15T00:00:00.000000",
      "startTime": "21:01:12",
      "rLength": "01:36:06",
      "ratePerc": null,
      "rateInK": "169.432",
      "shr": null,
      "description2": null,
      "rateInKAll": null,
      "live": 0
    },
    {
      "id": "135655",
      "period": "daily",
      "reportType": "south",
      "dateImport": "2022-09-16T00:00:00.000000",
      "dateResult": "2022-09-15T00:00:00.000000",
      "ranking": "12",
      "description": "GOOD DOCTOR",
      "category": null,
      "channel": "La Une",
      "dateDiff": "2022-09-15T00:00:00.000000",
      "startTime": "20:36:24",
      "rLength": "00:41:13",
      "ratePerc": null,
      "rateInK": "158.695",
      "shr": null,
      "description2": null,
      "rateInKAll": null,
      "live": 0
    },
    {
      "id": "135656",
      "period": "daily",
      "reportType": "south",
      "dateImport": "2022-09-16T00:00:00.000000",
      "dateResult": "2022-09-15T00:00:00.000000",
      "ranking": "13",
      "description": "LES 12 COUPS DE MIDI!",
      "category": null,
      "channel": "TF1",
      "dateDiff": "2022-09-15T00:00:00.000000",
      "startTime": "11:51:49",
      "rLength": "00:45:56",
      "ratePerc": null,
      "rateInK": "156.758",
      "shr": null,
      "description2": null,
      "rateInKAll": null,
      "live": 0
    },
    {
      "id": "135657",
      "period": "daily",
      "reportType": "south",
      "dateImport": "2022-09-16T00:00:00.000000",
      "dateResult": "2022-09-15T00:00:00.000000",
      "ranking": "14",
      "description": "HISTOIRES DE FAMILLES",
      "category": null,
      "channel": "RTL-TVI",
      "dateDiff": "2022-09-15T00:00:00.000000",
      "startTime": "13:48:15",
      "rLength": "00:27:36",
      "ratePerc": null,
      "rateInK": "152.282",
      "shr": null,
      "description2": null,
      "rateInKAll": null,
      "live": 0
    },
    {
      "id": "135658",
      "period": "daily",
      "reportType": "south",
      "dateImport": "2022-09-16T00:00:00.000000",
      "dateResult": "2022-09-15T00:00:00.000000",
      "ranking": "15",
      "description": "AFFAIRE CONCLUE, TOUT LE MONDE A QUELQUE CHOSE A VENDRE",
      "category": null,
      "channel": "La Une",
      "dateDiff": "2022-09-15T00:00:00.000000",
      "startTime": "13:42:32",
      "rLength": "00:42:45",
      "ratePerc": null,
      "rateInK": "151.839",
      "shr": null,
      "description2": null,
      "rateInKAll": null,
      "live": 0
    },
    {
      "id": "135659",
      "period": "daily",
      "reportType": "south",
      "dateImport": "2022-09-16T00:00:00.000000",
      "dateResult": "2022-09-15T00:00:00.000000",
      "ranking": "16",
      "description": "ON N'EST PAS DES PIGEONS!",
      "category": null,
      "channel": "La Une",
      "dateDiff": "2022-09-15T00:00:00.000000",
      "startTime": "18:29:54",
      "rLength": "00:41:22",
      "ratePerc": null,
      "rateInK": "137.914",
      "shr": null,
      "description2": null,
      "rateInKAll": null,
      "live": 0
    },
    {
      "id": "135660",
      "period": "daily",
      "reportType": "south",
      "dateImport": "2022-09-16T00:00:00.000000",
      "dateResult": "2022-09-15T00:00:00.000000",
      "ranking": "17",
      "description": "COMMISSAIRE MAGELLAN",
      "category": null,
      "channel": "La Une",
      "dateDiff": "2022-09-15T00:00:00.000000",
      "startTime": "15:19:12",
      "rLength": "01:32:09",
      "ratePerc": null,
      "rateInK": "116.449",
      "shr": null,
      "description2": null,
      "rateInKAll": null,
      "live": 0
    },
    {
      "id": "135661",
      "period": "daily",
      "reportType": "south",
      "dateImport": "2022-09-16T00:00:00.000000",
      "dateResult": "2022-09-15T00:00:00.000000",
      "ranking": "18",
      "description": "PLUS BELLE LA VIE",
      "category": null,
      "channel": "Tipik",
      "dateDiff": "2022-09-15T00:00:00.000000",
      "startTime": "13:31:52",
      "rLength": "00:25:06",
      "ratePerc": null,
      "rateInK": "83.988",
      "shr": null,
      "description2": null,
      "rateInKAll": null,
      "live": 0
    },
    {
      "id": "135662",
      "period": "daily",
      "reportType": "south",
      "dateImport": "2022-09-16T00:00:00.000000",
      "dateResult": "2022-09-15T00:00:00.000000",
      "ranking": "19",
      "description": "PETITS MEURTRES SUR LE CAMPUS, AFFAIRE CLASSEE",
      "category": null,
      "channel": "RTL-TVI",
      "dateDiff": "2022-09-15T00:00:00.000000",
      "startTime": "14:26:24",
      "rLength": "01:22:54",
      "ratePerc": null,
      "rateInK": "79.880",
      "shr": null,
      "description2": null,
      "rateInKAll": null,
      "live": 0
    },
    {
      "id": "135663",
      "period": "daily",
      "reportType": "south",
      "dateImport": "2022-09-16T00:00:00.000000",
      "dateResult": "2022-09-15T00:00:00.000000",
      "ranking": "20",
      "description": "VISE LE COEUR",
      "category": null,
      "channel": "TF1",
      "dateDiff": "2022-09-15T00:00:00.000000",
      "startTime": "21:14:04",
      "rLength": "00:53:56",
      "ratePerc": null,
      "rateInK": "79.115",
      "shr": null,
      "description2": null,
      "rateInKAll": null,
      "live": 0
    },
    {
      "id": "135664",
      "period": "daily",
      "reportType": "north",
      "dateImport": "2022-09-16T00:00:00.000000",
      "dateResult": "2022-09-15T00:00:00.000000",
      "ranking": "1",
      "description": "THUIS",
      "category": null,
      "channel": "EEN",
      "dateDiff": "2022-09-15T00:00:00.000000",
      "startTime": "20:15:11",
      "rLength": "00:25:21",
      "ratePerc": null,
      "rateInK": "1.051.269",
      "shr": null,
      "description2": null,
      "rateInKAll": null,
      "live": 0
    },
    {
      "id": "135665",
      "period": "daily",
      "reportType": "north",
      "dateImport": "2022-09-16T00:00:00.000000",
      "dateResult": "2022-09-15T00:00:00.000000",
      "ranking": "2",
      "description": "HET 7 UUR-JOURNAAL",
      "category": null,
      "channel": "EEN",
      "dateDiff": "2022-09-15T00:00:00.000000",
      "startTime": "19:00:02",
      "rLength": "00:44:25",
      "ratePerc": null,
      "rateInK": "863.421",
      "shr": null,
      "description2": null,
      "rateInKAll": null,
      "live": 0
    },
    {
      "id": "135666",
      "period": "daily",
      "reportType": "north",
      "dateImport": "2022-09-16T00:00:00.000000",
      "dateResult": "2022-09-15T00:00:00.000000",
      "ranking": "3",
      "description": "IEDEREEN BEROEMD",
      "category": null,
      "channel": "EEN",
      "dateDiff": "2022-09-15T00:00:00.000000",
      "startTime": "19:47:59",
      "rLength": "00:18:54",
      "ratePerc": null,
      "rateInK": "745.483",
      "shr": null,
      "description2": null,
      "rateInKAll": null,
      "live": 0
    },
    {
      "id": "135667",
      "period": "daily",
      "reportType": "north",
      "dateImport": "2022-09-16T00:00:00.000000",
      "dateResult": "2022-09-15T00:00:00.000000",
      "ranking": "4",
      "description": "DE ALLERSLIMSTE MENS TER WERELD",
      "category": null,
      "channel": "PLAY4",
      "dateDiff": "2022-09-15T00:00:00.000000",
      "startTime": "21:01:54",
      "rLength": "00:55:57",
      "ratePerc": null,
      "rateInK": "677.544",
      "shr": null,
      "description2": null,
      "rateInKAll": null,
      "live": 0
    },
    {
      "id": "135668",
      "period": "daily",
      "reportType": "north",
      "dateImport": "2022-09-16T00:00:00.000000",
      "dateResult": "2022-09-15T00:00:00.000000",
      "ranking": "5",
      "description": "NIEUWS 19U VTM",
      "category": null,
      "channel": "VTM",
      "dateDiff": "2022-09-15T00:00:00.000000",
      "startTime": "18:59:38",
      "rLength": "00:51:50",
      "ratePerc": null,
      "rateInK": "615.242",
      "shr": null,
      "description2": null,
      "rateInKAll": null,
      "live": 0
    },
    {
      "id": "135669",
      "period": "daily",
      "reportType": "north",
      "dateImport": "2022-09-16T00:00:00.000000",
      "dateResult": "2022-09-15T00:00:00.000000",
      "ranking": "6",
      "description": "POLITIE 24/7",
      "category": null,
      "channel": "EEN",
      "dateDiff": "2022-09-15T00:00:00.000000",
      "startTime": "20:43:15",
      "rLength": "00:44:32",
      "ratePerc": null,
      "rateInK": "528.187",
      "shr": null,
      "description2": null,
      "rateInKAll": null,
      "live": 0
    },
    {
      "id": "135670",
      "period": "daily",
      "reportType": "north",
      "dateImport": "2022-09-16T00:00:00.000000",
      "dateResult": "2022-09-15T00:00:00.000000",
      "ranking": "7",
      "description": "FAMILIE",
      "category": null,
      "channel": "VTM",
      "dateDiff": "2022-09-15T00:00:00.000000",
      "startTime": "20:02:07",
      "rLength": "00:25:07",
      "ratePerc": null,
      "rateInK": "513.817",
      "shr": null,
      "description2": null,
      "rateInKAll": null,
      "live": 0
    },
    {
      "id": "135671",
      "period": "daily",
      "reportType": "north",
      "dateImport": "2022-09-16T00:00:00.000000",
      "dateResult": "2022-09-15T00:00:00.000000",
      "ranking": "8",
      "description": "BLOKKEN",
      "category": null,
      "channel": "EEN",
      "dateDiff": "2022-09-15T00:00:00.000000",
      "startTime": "18:29:16",
      "rLength": "00:27:12",
      "ratePerc": null,
      "rateInK": "436.775",
      "shr": null,
      "description2": null,
      "rateInKAll": null,
      "live": 0
    },
    {
      "id": "135672",
      "period": "daily",
      "reportType": "north",
      "dateImport": "2022-09-16T00:00:00.000000",
      "dateResult": "2022-09-15T00:00:00.000000",
      "ranking": "9",
      "description": "HET 1 UUR-JOURNAAL",
      "category": null,
      "channel": "EEN",
      "dateDiff": "2022-09-15T00:00:00.000000",
      "startTime": "13:00:02",
      "rLength": "00:25:22",
      "ratePerc": null,
      "rateInK": "384.549",
      "shr": null,
      "description2": null,
      "rateInKAll": null,
      "live": 0
    },
    {
      "id": "135673",
      "period": "daily",
      "reportType": "north",
      "dateImport": "2022-09-16T00:00:00.000000",
      "dateResult": "2022-09-15T00:00:00.000000",
      "ranking": "10",
      "description": "HET JACHTSEIZOEN",
      "category": null,
      "channel": "VTM",
      "dateDiff": "2022-09-15T00:00:00.000000",
      "startTime": "20:36:40",
      "rLength": "00:41:57",
      "ratePerc": null,
      "rateInK": "298.604",
      "shr": null,
      "description2": null,
      "rateInKAll": null,
      "live": 0
    },
    {
      "id": "135674",
      "period": "daily",
      "reportType": "north",
      "dateImport": "2022-09-16T00:00:00.000000",
      "dateResult": "2022-09-15T00:00:00.000000",
      "ranking": "11",
      "description": "LISA",
      "category": null,
      "channel": "VTM",
      "dateDiff": "2022-09-15T00:00:00.000000",
      "startTime": "18:21:56",
      "rLength": "00:23:22",
      "ratePerc": null,
      "rateInK": "260.531",
      "shr": null,
      "description2": null,
      "rateInKAll": null,
      "live": 0
    },
    {
      "id": "135675",
      "period": "daily",
      "reportType": "north",
      "dateImport": "2022-09-16T00:00:00.000000",
      "dateResult": "2022-09-15T00:00:00.000000",
      "ranking": "12",
      "description": "ALLOO BIJ DE VERKEERSPOLITIE",
      "category": null,
      "channel": "VTM",
      "dateDiff": "2022-09-15T00:00:00.000000",
      "startTime": "21:36:06",
      "rLength": "00:56:35",
      "ratePerc": null,
      "rateInK": "244.934",
      "shr": null,
      "description2": null,
      "rateInKAll": null,
      "live": 0
    },
    {
      "id": "135676",
      "period": "daily",
      "reportType": "north",
      "dateImport": "2022-09-16T00:00:00.000000",
      "dateResult": "2022-09-15T00:00:00.000000",
      "ranking": "13",
      "description": "HET JOURNAAL LAAT",
      "category": null,
      "channel": "EEN",
      "dateDiff": "2022-09-15T00:00:00.000000",
      "startTime": "22:52:20",
      "rLength": "00:28:23",
      "ratePerc": null,
      "rateInK": "224.111",
      "shr": null,
      "description2": null,
      "rateInKAll": null,
      "live": 0
    },
    {
      "id": "135677",
      "period": "daily",
      "reportType": "north",
      "dateImport": "2022-09-16T00:00:00.000000",
      "dateResult": "2022-09-15T00:00:00.000000",
      "ranking": "14",
      "description": "DAGELIJKSE KOST",
      "category": null,
      "channel": "EEN",
      "dateDiff": "2022-09-15T00:00:00.000000",
      "startTime": "18:11:09",
      "rLength": "00:15:01",
      "ratePerc": null,
      "rateInK": "212.508",
      "shr": null,
      "description2": null,
      "rateInKAll": null,
      "live": 0
    },
    {
      "id": "135678",
      "period": "daily",
      "reportType": "north",
      "dateImport": "2022-09-16T00:00:00.000000",
      "dateResult": "2022-09-15T00:00:00.000000",
      "ranking": "15",
      "description": "VB. C3 UEFA SCHIFT - UNION ST-GILLOISE/MALMO",
      "category": null,
      "channel": "Canvas",
      "dateDiff": "2022-09-15T00:00:00.000000",
      "startTime": "21:00:22",
      "rLength": "01:37:08",
      "ratePerc": null,
      "rateInK": "208.619",
      "shr": null,
      "description2": null,
      "rateInKAll": null,
      "live": 0
    },
    {
      "id": "135679",
      "period": "daily",
      "reportType": "north",
      "dateImport": "2022-09-16T00:00:00.000000",
      "dateResult": "2022-09-15T00:00:00.000000",
      "ranking": "16",
      "description": "DE KLIM VAN JE LEVEN",
      "category": null,
      "channel": "EEN",
      "dateDiff": "2022-09-15T00:00:00.000000",
      "startTime": "21:31:30",
      "rLength": "00:33:29",
      "ratePerc": null,
      "rateInK": "207.734",
      "shr": null,
      "description2": null,
      "rateInKAll": null,
      "live": 0
    },
    {
      "id": "135680",
      "period": "daily",
      "reportType": "north",
      "dateImport": "2022-09-16T00:00:00.000000",
      "dateResult": "2022-09-15T00:00:00.000000",
      "ranking": "17",
      "description": "WITSE",
      "category": null,
      "channel": "EEN",
      "dateDiff": "2022-09-15T00:00:00.000000",
      "startTime": "17:12:47",
      "rLength": "00:51:25",
      "ratePerc": null,
      "rateInK": "204.229",
      "shr": null,
      "description2": null,
      "rateInKAll": null,
      "live": 0
    }
  ]
}