{
  "hydra:member": [
    {
      "id": "136652",
      "period": "daily",
      "reportType": "south",
      "dateImport": "2022-10-04T00:00:00.000000",
      "dateResult": "2022-10-03T00:00:00.000000",
      "ranking": "8",
      "description": "LES 12 COUPS DE MIDI!",
      "category": null,
      "channel": "TF1",
      "dateDiff": "2022-10-03T00:00:00.000000",
      "startTime": "11:55:44",
      "rLength": "00:45:19",
      "ratePerc": null,
      "rateInK": "209.518",
      "shr": null,
      "description2": null,
      "rateInKAll": null,
      "live": 0
    },
    {
      "id": "136653",
      "period": "daily",
      "reportType": "south",
      "dateImport": "2022-10-04T00:00:00.000000",
      "dateResult": "2022-10-03T00:00:00.000000",
      "ranking": "9",
      "description": "LES TUCHE 3",
      "category": null,
      "channel": "La Une",
      "dateDiff": "2022-10-03T00:00:00.000000",
      "startTime": "20:32:52",
      "rLength": "01:26:18",
      "ratePerc": null,
      "rateInK": "193.319",
      "shr": null,
      "description2": null,
      "rateInKAll": null,
      "live": 0
    },
    {
      "id": "136654",
      "period": "daily",
      "reportType": "south",
      "dateImport": "2022-10-04T00:00:00.000000",
      "dateResult": "2022-10-03T00:00:00.000000",
      "ranking": "10",
      "description": "ON N'EST PAS DES PIGEONS!",
      "category": null,
      "channel": "La Une",
      "dateDiff": "2022-10-03T00:00:00.000000",
      "startTime": "18:29:58",
      "rLength": "00:41:08",
      "ratePerc": null,
      "rateInK": "166.095",
      "shr": null,
      "description2": null,
      "rateInKAll": null,
      "live": 0
    },
    {
      "id": "136655",
      "period": "daily",
      "reportType": "south",
      "dateImport": "2022-10-04T00:00:00.000000",
      "dateResult": "2022-10-03T00:00:00.000000",
      "ranking": "11",
      "description": "DEMAIN NOUS APPARTIENT",
      "category": null,
      "channel": "La Une",
      "dateDiff": "2022-10-03T00:00:00.000000",
      "startTime": "17:56:01",
      "rLength": "00:27:32",
      "ratePerc": null,
      "rateInK": "164.109",
      "shr": null,
      "description2": null,
      "rateInKAll": null,
      "live": 0
    },
    {
      "id": "136656",
      "period": "daily",
      "reportType": "south",
      "dateImport": "2022-10-04T00:00:00.000000",
      "dateResult": "2022-10-03T00:00:00.000000",
      "ranking": "12",
      "description": "ICI TOUT COMMENCE",
      "category": null,
      "channel": "La Une",
      "dateDiff": "2022-10-03T00:00:00.000000",
      "startTime": "17:22:07",
      "rLength": "00:28:08",
      "ratePerc": null,
      "rateInK": "160.328",
      "shr": null,
      "description2": null,
      "rateInKAll": null,
      "live": 0
    },
    {
      "id": "136657",
      "period": "daily",
      "reportType": "south",
      "dateImport": "2022-10-04T00:00:00.000000",
      "dateResult": "2022-10-03T00:00:00.000000",
      "ranking": "13",
      "description": "AFFAIRE CONCLUE, TOUT LE MONDE A QUELQUE CHOSE A VENDRE",
      "category": null,
      "channel": "La Une",
      "dateDiff": "2022-10-03T00:00:00.000000",
      "startTime": "13:42:28",
      "rLength": "00:42:38",
      "ratePerc": null,
      "rateInK": "156.861",
      "shr": null,
      "description2": null,
      "rateInKAll": null,
      "live": 0
    },
    {
      "id": "136658",
      "period": "daily",
      "reportType": "south",
      "dateImport": "2022-10-04T00:00:00.000000",
      "dateResult": "2022-10-03T00:00:00.000000",
      "ranking": "14",
      "description": "HISTOIRES DE FAMILLES",
      "category": null,
      "channel": "RTL-TVI",
      "dateDiff": "2022-10-03T00:00:00.000000",
      "startTime": "13:44:34",
      "rLength": "00:29:24",
      "ratePerc": null,
      "rateInK": "156.664",
      "shr": null,
      "description2": null,
      "rateInKAll": null,
      "live": 0
    },
    {
      "id": "136659",
      "period": "daily",
      "reportType": "south",
      "dateImport": "2022-10-04T00:00:00.000000",
      "dateResult": "2022-10-03T00:00:00.000000",
      "ranking": "15",
      "description": "MANHATTAN LOCKDOWN",
      "category": null,
      "channel": "Club RTL",
      "dateDiff": "2022-10-03T00:00:00.000000",
      "startTime": "20:05:06",
      "rLength": "01:35:26",
      "ratePerc": null,
      "rateInK": "110.883",
      "shr": null,
      "description2": null,
      "rateInKAll": null,
      "live": 0
    },
    {
      "id": "136660",
      "period": "daily",
      "reportType": "south",
      "dateImport": "2022-10-04T00:00:00.000000",
      "dateResult": "2022-10-03T00:00:00.000000",
      "ranking": "16",
      "description": "COMMISSAIRE MAGELLAN",
      "category": null,
      "channel": "La Une",
      "dateDiff": "2022-10-03T00:00:00.000000",
      "startTime": "15:18:06",
      "rLength": "01:34:19",
      "ratePerc": null,
      "rateInK": "104.739",
      "shr": null,
      "description2": null,
      "rateInKAll": null,
      "live": 0
    },
    {
      "id": "136661",
      "period": "daily",
      "reportType": "south",
      "dateImport": "2022-10-04T00:00:00.000000",
      "dateResult": "2022-10-03T00:00:00.000000",
      "ranking": "17",
      "description": "STUDIO FOOT - LA TRIBUNE",
      "category": null,
      "channel": "Tipik",
      "dateDiff": "2022-10-03T00:00:00.000000",
      "startTime": "20:29:58",
      "rLength": "01:57:18",
      "ratePerc": null,
      "rateInK": "96.784",
      "shr": null,
      "description2": null,
      "rateInKAll": null,
      "live": 0
    },
    {
      "id": "136662",
      "period": "daily",
      "reportType": "south",
      "dateImport": "2022-10-04T00:00:00.000000",
      "dateResult": "2022-10-03T00:00:00.000000",
      "ranking": "18",
      "description": "OBJECTIF TOP CHEF",
      "category": null,
      "channel": "RTL-TVI",
      "dateDiff": "2022-10-03T00:00:00.000000",
      "startTime": "17:11:23",
      "rLength": "00:50:04",
      "ratePerc": null,
      "rateInK": "95.954",
      "shr": null,
      "description2": null,
      "rateInKAll": null,
      "live": 0
    },
    {
      "id": "136663",
      "period": "daily",
      "reportType": "south",
      "dateImport": "2022-10-04T00:00:00.000000",
      "dateResult": "2022-10-03T00:00:00.000000",
      "ranking": "19",
      "description": "LE 20 HEURES",
      "category": null,
      "channel": "TF1",
      "dateDiff": "2022-10-03T00:00:00.000000",
      "startTime": "19:57:57",
      "rLength": "00:45:22",
      "ratePerc": null,
      "rateInK": "94.589",
      "shr": null,
      "description2": null,
      "rateInKAll": null,
      "live": 0
    },
    {
      "id": "136664",
      "period": "daily",
      "reportType": "south",
      "dateImport": "2022-10-04T00:00:00.000000",
      "dateResult": "2022-10-03T00:00:00.000000",
      "ranking": "20",
      "description": "PLUS BELLE LA VIE",
      "category": null,
      "channel": "Tipik",
      "dateDiff": "2022-10-03T00:00:00.000000",
      "startTime": "13:29:37",
      "rLength": "00:26:03",
      "ratePerc": null,
      "rateInK": "90.535",
      "shr": null,
      "description2": null,
      "rateInKAll": null,
      "live": 0
    },
    {
      "id": "136665",
      "period": "daily",
      "reportType": "north",
      "dateImport": "2022-10-04T00:00:00.000000",
      "dateResult": "2022-10-03T00:00:00.000000",
      "ranking": "1",
      "description": "THUIS",
      "category": null,
      "channel": "EEN",
      "dateDiff": "2022-10-03T00:00:00.000000",
      "startTime": "20:07:00",
      "rLength": "00:25:12",
      "ratePerc": null,
      "rateInK": "959.143",
      "shr": null,
      "description2": null,
      "rateInKAll": null,
      "live": 0
    },
    {
      "id": "136666",
      "period": "daily",
      "reportType": "north",
      "dateImport": "2022-10-04T00:00:00.000000",
      "dateResult": "2022-10-03T00:00:00.000000",
      "ranking": "2",
      "description": "HET 7 UUR-JOURNAAL",
      "category": null,
      "channel": "EEN",
      "dateDiff": "2022-10-03T00:00:00.000000",
      "startTime": "19:00:03",
      "rLength": "00:40:50",
      "ratePerc": null,
      "rateInK": "918.250",
      "shr": null,
      "description2": null,
      "rateInKAll": null,
      "live": 0
    },
    {
      "id": "136667",
      "period": "daily",
      "reportType": "north",
      "dateImport": "2022-10-04T00:00:00.000000",
      "dateResult": "2022-10-03T00:00:00.000000",
      "ranking": "3",
      "description": "DOWN THE ROAD",
      "category": null,
      "channel": "EEN",
      "dateDiff": "2022-10-03T00:00:00.000000",
      "startTime": "20:33:51",
      "rLength": "00:56:08",
      "ratePerc": null,
      "rateInK": "833.555",
      "shr": null,
      "description2": null,
      "rateInKAll": null,
      "live": 0
    },
    {
      "id": "136668",
      "period": "daily",
      "reportType": "north",
      "dateImport": "2022-10-04T00:00:00.000000",
      "dateResult": "2022-10-03T00:00:00.000000",
      "ranking": "4",
      "description": "IEDEREEN BEROEMD",
      "category": null,
      "channel": "EEN",
      "dateDiff": "2022-10-03T00:00:00.000000",
      "startTime": "19:41:15",
      "rLength": "00:19:57",
      "ratePerc": null,
      "rateInK": "810.704",
      "shr": null,
      "description2": null,
      "rateInKAll": null,
      "live": 0
    },
    {
      "id": "136669",
      "period": "daily",
      "reportType": "north",
      "dateImport": "2022-10-04T00:00:00.000000",
      "dateResult": "2022-10-03T00:00:00.000000",
      "ranking": "5",
      "description": "DE ALLERSLIMSTE MENS TER WERELD",
      "category": null,
      "channel": "PLAY4",
      "dateDiff": "2022-10-03T00:00:00.000000",
      "startTime": "20:59:35",
      "rLength": "01:01:19",
      "ratePerc": null,
      "rateInK": "623.967",
      "shr": null,
      "description2": null,
      "rateInKAll": null,
      "live": 0
    },
    {
      "id": "136670",
      "period": "daily",
      "reportType": "north",
      "dateImport": "2022-10-04T00:00:00.000000",
      "dateResult": "2022-10-03T00:00:00.000000",
      "ranking": "6",
      "description": "NIEUWS 19U VTM",
      "category": null,
      "channel": "VTM",
      "dateDiff": "2022-10-03T00:00:00.000000",
      "startTime": "18:59:38",
      "rLength": "00:51:32",
      "ratePerc": null,
      "rateInK": "587.321",
      "shr": null,
      "description2": null,
      "rateInKAll": null,
      "live": 0
    },
    {
      "id": "136671",
      "period": "daily",
      "reportType": "north",
      "dateImport": "2022-10-04T00:00:00.000000",
      "dateResult": "2022-10-03T00:00:00.000000",
      "ranking": "7",
      "description": "BLOKKEN",
      "category": null,
      "channel": "EEN",
      "dateDiff": "2022-10-03T00:00:00.000000",
      "startTime": "18:29:10",
      "rLength": "00:27:07",
      "ratePerc": null,
      "rateInK": "529.084",
      "shr": null,
      "description2": null,
      "rateInKAll": null,
      "live": 0
    },
    {
      "id": "136672",
      "period": "daily",
      "reportType": "north",
      "dateImport": "2022-10-04T00:00:00.000000",
      "dateResult": "2022-10-03T00:00:00.000000",
      "ranking": "8",
      "description": "FAMILIE",
      "category": null,
      "channel": "VTM",
      "dateDiff": "2022-10-03T00:00:00.000000",
      "startTime": "20:01:24",
      "rLength": "00:24:51",
      "ratePerc": null,
      "rateInK": "518.760",
      "shr": null,
      "description2": null,
      "rateInKAll": null,
      "live": 0
    },
    {
      "id": "136673",
      "period": "daily",
      "reportType": "north",
      "dateImport": "2022-10-04T00:00:00.000000",
      "dateResult": "2022-10-03T00:00:00.000000",
      "ranking": "9",
      "description": "BLIND GETROUWD",
      "category": null,
      "channel": "VTM",
      "dateDiff": "2022-10-03T00:00:00.000000",
      "startTime": "20:35:46",
      "rLength": "00:52:39",
      "ratePerc": null,
      "rateInK": "505.576",
      "shr": null,
      "description2": null,
      "rateInKAll": null,
      "live": 0
    },
    {
      "id": "136674",
      "period": "daily",
      "reportType": "north",
      "dateImport": "2022-10-04T00:00:00.000000",
      "dateResult": "2022-10-03T00:00:00.000000",
      "ranking": "10",
      "description": "THE REPAIR SHOP",
      "category": null,
      "channel": "EEN",
      "dateDiff": "2022-10-03T00:00:00.000000",
      "startTime": "21:31:47",
      "rLength": "00:40:45",
      "ratePerc": null,
      "rateInK": "404.179",
      "shr": null,
      "description2": null,
      "rateInKAll": null,
      "live": 0
    },
    {
      "id": "136675",
      "period": "daily",
      "reportType": "north",
      "dateImport": "2022-10-04T00:00:00.000000",
      "dateResult": "2022-10-03T00:00:00.000000",
      "ranking": "11",
      "description": "HET 1 UUR-JOURNAAL",
      "category": null,
      "channel": "EEN",
      "dateDiff": "2022-10-03T00:00:00.000000",
      "startTime": "13:00:02",
      "rLength": "00:30:17",
      "ratePerc": null,
      "rateInK": "369.571",
      "shr": null,
      "description2": null,
      "rateInKAll": null,
      "live": 0
    },
    {
      "id": "136676",
      "period": "daily",
      "reportType": "north",
      "dateImport": "2022-10-04T00:00:00.000000",
      "dateResult": "2022-10-03T00:00:00.000000",
      "ranking": "12",
      "description": "LISA",
      "category": null,
      "channel": "VTM",
      "dateDiff": "2022-10-03T00:00:00.000000",
      "startTime": "18:23:29",
      "rLength": "00:22:08",
      "ratePerc": null,
      "rateInK": "274.489",
      "shr": null,
      "description2": null,
      "rateInKAll": null,
      "live": 0
    },
    {
      "id": "136677",
      "period": "daily",
      "reportType": "north",
      "dateImport": "2022-10-04T00:00:00.000000",
      "dateResult": "2022-10-03T00:00:00.000000",
      "ranking": "13",
      "description": "DAGELIJKSE KOST",
      "category": null,
      "channel": "EEN",
      "dateDiff": "2022-10-03T00:00:00.000000",
      "startTime": "18:10:59",
      "rLength": "00:15:14",
      "ratePerc": null,
      "rateInK": "250.966",
      "shr": null,
      "description2": null,
      "rateInKAll": null,
      "live": 0
    },
    {
      "id": "136678",
      "period": "daily",
      "reportType": "north",
      "dateImport": "2022-10-04T00:00:00.000000",
      "dateResult": "2022-10-03T00:00:00.000000",
      "ranking": "14",
      "description": "HET JOURNAAL LAAT",
      "category": null,
      "channel": "EEN",
      "dateDiff": "2022-10-03T00:00:00.000000",
      "startTime": "22:59:45",
      "rLength": "00:27:06",
      "ratePerc": null,
      "rateInK": "242.031",
      "shr": null,
      "description2": null,
      "rateInKAll": null,
      "live": 0
    },
    {
      "id": "136679",
      "period": "daily",
      "reportType": "north",
      "dateImport": "2022-10-04T00:00:00.000000",
      "dateResult": "2022-10-03T00:00:00.000000",
      "ranking": "15",
      "description": "DE AFSPRAAK",
      "category": null,
      "channel": "Canvas",
      "dateDiff": "2022-10-03T00:00:00.000000",
      "startTime": "20:30:03",
      "rLength": "00:46:49",
      "ratePerc": null,
      "rateInK": "241.303",
      "shr": null,
      "description2": null,
      "rateInKAll": null,
      "live": 0
    },
    {
      "id": "136680",
      "period": "daily",
      "reportType": "north",
      "dateImport": "2022-10-04T00:00:00.000000",
      "dateResult": "2022-10-03T00:00:00.000000",
      "ranking": "16",
      "description": "POLITIE 24/7",
      "category": null,
      "channel": "EEN",
      "dateDiff": "2022-10-03T00:00:00.000000",
      "startTime": "22:14:23",
      "rLength": "00:44:02",
      "ratePerc": null,
      "rateInK": "241.193",
      "shr": null,
      "description2": null,
      "rateInKAll": null,
      "live": 0
    },
    {
      "id": "136681",
      "period": "daily",
      "reportType": "north",
      "dateImport": "2022-10-04T00:00:00.000000",
      "dateResult": "2022-10-03T00:00:00.000000",
      "ranking": "17",
      "description": "NIEUWS 13U VTM",
      "category": null,
      "channel": "VTM",
      "dateDiff": "2022-10-03T00:00:00.000000",
      "startTime": "12:59:37",
      "rLength": "00:26:34",
      "ratePerc": null,
      "rateInK": "238.570",
      "shr": null,
      "description2": null,
      "rateInKAll": null,
      "live": 0
    }
  ]
}